p2/word/coder.vhdl
library ieee;
use ieee.std_logic_1164.all;

entity coder is
	port(
		ring:	in	std_logic_vector(5 downto 0);
		code:	out	std_logic_vector(6 downto 0)
	);
end coder;

architecture arch of coder is
begin
	with ring select code <=
		"1000011" when "011111",
		"1000001" when "101111",
		"1001011" when "110111",
		"1000101" when "111011",
		"1111111" when others;
end arch;

p2/word/counter.vhdl
library ieee;
use ieee.std_logic_1164.all;

entity counter is
	port(
		clock:	in	std_logic;
		enable:	in	std_logic;
		ring:	out	std_logic_vector(5 downto 0)
	);
end counter;

architecture arch of counter is
	signal sshift: std_logic_vector(5 downto 0);
begin
	pcount: process(clock)
	begin
		if( clock'event and clock = '1' ) then
			case enable is
				when '0' =>
					ring <= (others => '0');
					sshift <= "011111";
				when '1' =>
					sshift(5) <= sshift(0);
					sshift(4 downto 0) <= sshift(5 downto 1);
					ring <= sshift;
				when others => null;
			end case;
		end if;
	end process pcount;
end arch;

p2/word/word.vhdl
library ieee;
library work;
use ieee.std_logic_1164.all;
use work.packageword.all;

entity word is
	port(
		clock:		inout	std_logic;
		enable:		in		std_logic;
		code:		out		std_logic_vector(6 downto 0);
		ring:		out		std_logic_vector(5 downto 0)
	);
end word;

architecture arch of word is
	signal bridge:	std_logic_vector(5 downto 0);
begin
	con0: counter	port map( clock => clock,  enable => enable, ring => bridge );
	con1: coder		port map( ring  => bridge, code   => code );
	ring <= bridge;
end arch;

p2/word/test.vhdl
library ieee;
use ieee.std_logic_1164.all;

entity test is
end test;

architecture arch of test is
	component word is
		port(
			clock:		inout	std_logic;
			enable:		in		std_logic;
			code:		out		std_logic_vector(6 downto 0);
			ring:		out		std_logic_vector(5 downto 0)
		);
	end component;
	signal clock:	std_logic;
	signal enable:	std_logic;
	signal ring:	std_logic_vector(5 downto 0);
	signal code:	std_logic_vector(6 downto 0);
	constant period:	time := 2 ns;
begin
	conn:	word port map( clock => clock, enable => enable, ring => ring, code => code );
	clockP: process
	begin
		clock <= '0';
		wait for period / 2;
		clock <= '1';
		wait for period / 2;
	end process;

	enableP: process
	begin
		enable <= '0';
		wait for period;
		enable <= '1';
		wait;
	end process;
end arch;

p2/word/sim.vcd
$date
  Thu Oct 28 18:53:07 2021
$end
$version
  GHDL v0
$end
$timescale
  1 fs
$end
$scope module standard $end
$upscope $end
$scope module std_logic_1164 $end
$upscope $end
$scope module packageword $end
$upscope $end
$scope module test $end
$var reg 1 ! clock $end
$var reg 1 " enable $end
$var reg 6 # ring[5:0] $end
$var reg 7 $ code[6:0] $end
$scope module conn $end
$var reg 1 % clock $end
$var reg 1 & enable $end
$var reg 7 ' code[6:0] $end
$var reg 6 ( ring[5:0] $end
$var reg 6 ) bridge[5:0] $end
$scope module con0 $end
$var reg 1 * clock $end
$var reg 1 + enable $end
$var reg 6 , ring[5:0] $end
$var reg 6 - sshift[5:0] $end
$upscope $end
$scope module con1 $end
$var reg 6 . ring[5:0] $end
$var reg 7 / code[6:0] $end
$upscope $end
$upscope $end
$upscope $end
$enddefinitions $end
#0
0!
0"
bUUUUUU #
b1111111 $
0%
0&
b1111111 '
bUUUUUU (
bUUUUUU )
0*
0+
bUUUUUU ,
bUUUUUU -
bUUUUUU .
b1111111 /
#1000000
1!
b000000 #
1%
b000000 (
b000000 )
1*
b000000 ,
b011111 -
b000000 .
#2000000
0!
1"
0%
1&
0*
1+
#3000000
1!
b011111 #
b1000011 $
1%
b1000011 '
b011111 (
b011111 )
1*
b011111 ,
b101111 -
b011111 .
b1000011 /
#4000000
0!
0%
0*
#5000000
1!
b101111 #
b1000001 $
1%
b1000001 '
b101111 (
b101111 )
1*
b101111 ,
b110111 -
b101111 .
b1000001 /
#6000000
0!
0%
0*
#7000000
1!
b110111 #
b1001011 $
1%
b1001011 '
b110111 (
b110111 )
1*
b110111 ,
b111011 -
b110111 .
b1001011 /
#8000000
0!
0%
0*
#9000000
1!
b111011 #
b1000101 $
1%
b1000101 '
b111011 (
b111011 )
1*
b111011 ,
b111101 -
b111011 .
b1000101 /
#10000000
0!
0%
0*
#11000000
1!
b111101 #
b1111111 $
1%
b1111111 '
b111101 (
b111101 )
1*
b111101 ,
b111110 -
b111101 .
b1111111 /
#12000000
0!
0%
0*
#13000000
1!
b111110 #
1%
b111110 (
b111110 )
1*
b111110 ,
b011111 -
b111110 .
#14000000
0!
0%
0*
#15000000
1!
b011111 #
b1000011 $
1%
b1000011 '
b011111 (
b011111 )
1*
b011111 ,
b101111 -
b011111 .
b1000011 /
#16000000
0!
0%
0*
#17000000
1!
b101111 #
b1000001 $
1%
b1000001 '
b101111 (
b101111 )
1*
b101111 ,
b110111 -
b101111 .
b1000001 /
#18000000
0!
0%
0*
#19000000
1!
b110111 #
b1001011 $
1%
b1001011 '
b110111 (
b110111 )
1*
b110111 ,
b111011 -
b110111 .
b1001011 /
#20000000
0!
0%
0*
#21000000
1!
b111011 #
b1000101 $
1%
b1000101 '
b111011 (
b111011 )
1*
b111011 ,
b111101 -
b111011 .
b1000101 /
#22000000
0!
0%
0*
#23000000
1!
b111101 #
b1111111 $
1%
b1111111 '
b111101 (
b111101 )
1*
b111101 ,
b111110 -
b111101 .
b1111111 /
#24000000
0!
0%
0*
#25000000
1!
b111110 #
1%
b111110 (
b111110 )
1*
b111110 ,
b011111 -
b111110 .
#26000000
0!
0%
0*
#27000000
1!
b011111 #
b1000011 $
1%
b1000011 '
b011111 (
b011111 )
1*
b011111 ,
b101111 -
b011111 .
b1000011 /
#28000000
0!
0%
0*
#29000000
1!
b101111 #
b1000001 $
1%
b1000001 '
b101111 (
b101111 )
1*
b101111 ,
b110111 -
b101111 .
b1000001 /
#30000000
0!
0%
0*
#31000000
1!
b110111 #
b1001011 $
1%
b1001011 '
b110111 (
b110111 )
1*
b110111 ,
b111011 -
b110111 .
b1001011 /
#32000000
0!
0%
0*
#33000000
1!
b111011 #
b1000101 $
1%
b1000101 '
b111011 (
b111011 )
1*
b111011 ,
b111101 -
b111011 .
b1000101 /
#34000000
0!
0%
0*
#35000000
1!
b111101 #
b1111111 $
1%
b1111111 '
b111101 (
b111101 )
1*
b111101 ,
b111110 -
b111101 .
b1111111 /
#36000000
0!
0%
0*
#37000000
1!
b111110 #
1%
b111110 (
b111110 )
1*
b111110 ,
b011111 -
b111110 .
#38000000
0!
0%
0*
#39000000
1!
b011111 #
b1000011 $
1%
b1000011 '
b011111 (
b011111 )
1*
b011111 ,
b101111 -
b011111 .
b1000011 /
#40000000
0!
0%
0*
#41000000
1!
b101111 #
b1000001 $
1%
b1000001 '
b101111 (
b101111 )
1*
b101111 ,
b110111 -
b101111 .
b1000001 /
#42000000
0!
0%
0*
#43000000
1!
b110111 #
b1001011 $
1%
b1001011 '
b110111 (
b110111 )
1*
b110111 ,
b111011 -
b110111 .
b1001011 /
#44000000
0!
0%
0*
#45000000
1!
b111011 #
b1000101 $
1%
b1000101 '
b111011 (
b111011 )
1*
b111011 ,
b111101 -
b111011 .
b1000101 /
#46000000
0!
0%
0*
#47000000
1!
b111101 #
b1111111 $
1%
b1111111 '
b111101 (
b111101 )
1*
b111101 ,
b111110 -
b111101 .
b1111111 /
#48000000
0!
0%
0*
#49000000
1!
b111110 #
1%
b111110 (
b111110 )
1*
b111110 ,
b011111 -
b111110 .
#50000000
0!
0%
0*
#51000000
1!
b011111 #
b1000011 $
1%
b1000011 '
b011111 (
b011111 )
1*
b011111 ,
b101111 -
b011111 .
b1000011 /
#52000000
0!
0%
0*
#53000000
1!
b101111 #
b1000001 $
1%
b1000001 '
b101111 (
b101111 )
1*
b101111 ,
b110111 -
b101111 .
b1000001 /
#54000000
0!
0%
0*
#55000000
1!
b110111 #
b1001011 $
1%
b1001011 '
b110111 (
b110111 )
1*
b110111 ,
b111011 -
b110111 .
b1001011 /
#56000000
0!
0%
0*
#57000000
1!
b111011 #
b1000101 $
1%
b1000101 '
b111011 (
b111011 )
1*
b111011 ,
b111101 -
b111011 .
b1000101 /
#58000000
0!
0%
0*
#59000000
1!
b111101 #
b1111111 $
1%
b1111111 '
b111101 (
b111101 )
1*
b111101 ,
b111110 -
b111101 .
b1111111 /
#60000000
0!
0%
0*
#61000000
1!
b111110 #
1%
b111110 (
b111110 )
1*
b111110 ,
b011111 -
b111110 .
#62000000
0!
0%
0*
#63000000
1!
b011111 #
b1000011 $
1%
b1000011 '
b011111 (
b011111 )
1*
b011111 ,
b101111 -
b011111 .
b1000011 /
#64000000
0!
0%
0*
#65000000
1!
b101111 #
b1000001 $
1%
b1000001 '
b101111 (
b101111 )
1*
b101111 ,
b110111 -
b101111 .
b1000001 /
#66000000
0!
0%
0*
#67000000
1!
b110111 #
b1001011 $
1%
b1001011 '
b110111 (
b110111 )
1*
b110111 ,
b111011 -
b110111 .
b1001011 /
#68000000
0!
0%
0*
#69000000
1!
b111011 #
b1000101 $
1%
b1000101 '
b111011 (
b111011 )
1*
b111011 ,
b111101 -
b111011 .
b1000101 /
#70000000
0!
0%
0*
#71000000
1!
b111101 #
b1111111 $
1%
b1111111 '
b111101 (
b111101 )
1*
b111101 ,
b111110 -
b111101 .
b1111111 /
#72000000
0!
0%
0*
#73000000
1!
b111110 #
1%
b111110 (
b111110 )
1*
b111110 ,
b011111 -
b111110 .
#74000000
0!
0%
0*
#75000000
1!
b011111 #
b1000011 $
1%
b1000011 '
b011111 (
b011111 )
1*
b011111 ,
b101111 -
b011111 .
b1000011 /
#76000000
0!
0%
0*
#77000000
1!
b101111 #
b1000001 $
1%
b1000001 '
b101111 (
b101111 )
1*
b101111 ,
b110111 -
b101111 .
b1000001 /
#78000000
0!
0%
0*
#79000000
1!
b110111 #
b1001011 $
1%
b1001011 '
b110111 (
b110111 )
1*
b110111 ,
b111011 -
b110111 .
b1001011 /
