p2/shifts/shift/shift_r_lr.vhdl
library ieee;
use ieee.std_logic_1164.all;

entity shift_r_lr is
	port(
		clks:	in	std_logic;
		ens:	in	std_logic;
		ins:	in	std_logic_vector(7 downto 0);
		outs:	out	std_logic_vector(7 downto 0)
	);
end shift_r_lr ;

architecture arch of shift_r_lr is
	signal sshift: std_logic_vector(7 downto 0);
begin
	pshift: process(clks)
	begin
	if( clks'event and clks = '1') then
		case ens is
			when '0' =>
				outs	<= (others => '0');
				sshift	<= ins;
			when '1' =>
				sshift(7) <= sshift(0);
				sshift(6  downto 0) <= sshift(7 downto 1);
				outs <= sshift;
			when others => null;
		end case;
	end if;
	end process pshift;
end arch;

p2/shifts/shift/shift_r_rl.vhdl
library ieee;
use ieee.std_logic_1164.all;

entity shift_r_rl is
	port(
		clks:	in	std_logic;
		ens:	in	std_logic;
		ins:	in	std_logic_vector(7 downto 0);
		outs:	out	std_logic_vector(7 downto 0)
	);
end shift_r_rl ;

architecture arch of shift_r_rl is
	signal sshift: std_logic_vector(7 downto 0);
begin
	pshift: process(clks)
	begin
	if( clks'event and clks = '1') then
		case ens is
			when '0' =>
				outs	<= (others => '0');
				sshift	<= ins;
			when '1' =>
				sshift(0) <= sshift(7);
				sshift(7  downto 1) <= sshift(6 downto 0);
				outs <= sshift;
			when others => null;
		end case;
	end if;
	end process pshift;
end arch;

p2/shifts/shift/shift_lr.vhdl
library ieee;
use ieee.std_logic_1164.all;

entity shift_lr is
	port(
		clks:	in	std_logic;
		ens:	in	std_logic;
		ins:	in	std_logic_vector(7 downto 0);
		outs:	out	std_logic_vector(7 downto 0)
	);
end shift_lr ;

architecture arch of shift_lr is
	signal sshift: std_logic_vector(7 downto 0);
begin
	pshift: process(clks)
	begin
	if( clks'event and clks = '1') then
		case ens is
			when '0' =>
				outs	<= (others => '0');
				sshift	<= ins;
			when '1' =>
				sshift(7) <= '0';
				sshift(6  downto 0) <= sshift(7 downto 1);
				outs <= sshift;
			when others => null;
		end case;
	end if;
	end process pshift;
end arch;

p2/shifts/shift/shift_rl.vhdl
library ieee;
use ieee.std_logic_1164.all;

entity shift_rl is
	port(
		clks:	in	std_logic;
		ens:	in	std_logic;
		ins:	in	std_logic_vector(7 downto 0);
		outs:	out	std_logic_vector(7 downto 0)
	);
end shift_rl ;

architecture arch of shift_rl is
	signal sshift: std_logic_vector(7 downto 0);
begin
	pshift: process(clks)
	begin
	if( clks'event and clks = '1') then
		case ens is
			when '0' =>
				outs	<= (others => '0');
				sshift	<= ins;
			when '1' =>
				sshift(0) <= '0';
				sshift(7  downto 1) <= sshift(6 downto 0);
				outs <= sshift;
			when others => null;
		end case;
	end if;
	end process pshift;
end arch;

p2/shifts/shift/test.vhdl
library ieee;
library work;
use ieee.std_logic_1164.all;
use work.packageshift.all;

entity test is
end test;

architecture arch of test is
	signal sclk: std_logic;
	signal sens: std_logic;

	signal sin: std_logic_vector(7 downto 0);

	signal sin0: std_logic_vector(7 downto 0);
	signal sin1: std_logic_vector(7 downto 0);
	signal sin2: std_logic_vector(7 downto 0);
	signal sin3: std_logic_vector(7 downto 0);

	signal o_rl:	std_logic_vector(7 downto 0);
	signal o_lr:	std_logic_vector(7 downto 0);
	signal o_r_rl:	std_logic_vector(7 downto 0);
	signal o_r_lr:	std_logic_vector(7 downto 0);

	constant period:	time := 2 ns;
begin

	con0: shift_rl		port map( clks => sclk, ens => sens, ins => sin0, outs => o_rl	  );
	con1: shift_lr		port map( clks => sclk, ens => sens, ins => sin1, outs => o_lr	  );
	con2: shift_r_rl	port map( clks => sclk, ens => sens, ins => sin2, outs => o_r_rl );
	con3: shift_r_lr	port map( clks => sclk, ens => sens, ins => sin3, outs => o_r_lr );

	sin <= "11000011";
	
	sin0 <= sin;
	sin1 <= sin;
	sin2 <= sin;
	sin3 <= sin;
	
	clk: process
	begin
		sclk <= '0';
		wait for period/2;
		sclk <= '1';
		wait for period/2;
	end process;

	init: process
	begin
		sens <= '0';
		wait for period;
		sens <= '1';
		wait;
	end process;
end arch;

p2/shifts/shift/sim.vcd
$date
  Mon Oct 18 11:39:39 2021
$end
$version
  GHDL v0
$end
$timescale
  1 fs
$end
$scope module standard $end
$upscope $end
$scope module std_logic_1164 $end
$upscope $end
$scope module packageshift $end
$upscope $end
$scope module test $end
$var reg 1 ! sclk $end
$var reg 1 " sens $end
$var reg 8 # sin[7:0] $end
$var reg 8 $ sin0[7:0] $end
$var reg 8 % sin1[7:0] $end
$var reg 8 & sin2[7:0] $end
$var reg 8 ' sin3[7:0] $end
$var reg 8 ( o_rl[7:0] $end
$var reg 8 ) o_lr[7:0] $end
$var reg 8 * o_r_rl[7:0] $end
$var reg 8 + o_r_lr[7:0] $end
$scope module con0 $end
$var reg 1 , clks $end
$var reg 1 - ens $end
$var reg 8 . ins[7:0] $end
$var reg 8 / outs[7:0] $end
$var reg 8 0 sshift[7:0] $end
$upscope $end
$scope module con1 $end
$var reg 1 1 clks $end
$var reg 1 2 ens $end
$var reg 8 3 ins[7:0] $end
$var reg 8 4 outs[7:0] $end
$var reg 8 5 sshift[7:0] $end
$upscope $end
$scope module con2 $end
$var reg 1 6 clks $end
$var reg 1 7 ens $end
$var reg 8 8 ins[7:0] $end
$var reg 8 9 outs[7:0] $end
$var reg 8 : sshift[7:0] $end
$upscope $end
$scope module con3 $end
$var reg 1 ; clks $end
$var reg 1 < ens $end
$var reg 8 = ins[7:0] $end
$var reg 8 > outs[7:0] $end
$var reg 8 ? sshift[7:0] $end
$upscope $end
$upscope $end
$enddefinitions $end
#0
0!
0"
b11000011 #
b11000011 $
b11000011 %
b11000011 &
b11000011 '
bUUUUUUUU (
bUUUUUUUU )
bUUUUUUUU *
bUUUUUUUU +
0,
0-
b11000011 .
bUUUUUUUU /
bUUUUUUUU 0
01
02
b11000011 3
bUUUUUUUU 4
bUUUUUUUU 5
06
07
b11000011 8
bUUUUUUUU 9
bUUUUUUUU :
0;
0<
b11000011 =
bUUUUUUUU >
bUUUUUUUU ?
#1000000
1!
b00000000 (
b00000000 )
b00000000 *
b00000000 +
1,
b00000000 /
b11000011 0
11
b00000000 4
b11000011 5
16
b00000000 9
b11000011 :
1;
b00000000 >
b11000011 ?
#2000000
0!
1"
0,
1-
01
12
06
17
0;
1<
#3000000
1!
b11000011 (
b11000011 )
b11000011 *
b11000011 +
1,
b11000011 /
b10000110 0
11
b11000011 4
b01100001 5
16
b11000011 9
b10000111 :
1;
b11000011 >
b11100001 ?
#4000000
0!
0,
01
06
0;
#5000000
1!
b10000110 (
b01100001 )
b10000111 *
b11100001 +
1,
b10000110 /
b00001100 0
11
b01100001 4
b00110000 5
16
b10000111 9
b00001111 :
1;
b11100001 >
b11110000 ?
#6000000
0!
0,
01
06
0;
#7000000
1!
b00001100 (
b00110000 )
b00001111 *
b11110000 +
1,
b00001100 /
b00011000 0
11
b00110000 4
b00011000 5
16
b00001111 9
b00011110 :
1;
b11110000 >
b01111000 ?
#8000000
0!
0,
01
06
0;
#9000000
1!
b00011000 (
b00011000 )
b00011110 *
b01111000 +
1,
b00011000 /
b00110000 0
11
b00011000 4
b00001100 5
16
b00011110 9
b00111100 :
1;
b01111000 >
b00111100 ?
#10000000
0!
0,
01
06
0;
#11000000
1!
b00110000 (
b00001100 )
b00111100 *
b00111100 +
1,
b00110000 /
b01100000 0
11
b00001100 4
b00000110 5
16
b00111100 9
b01111000 :
1;
b00111100 >
b00011110 ?
#12000000
0!
0,
01
06
0;
#13000000
1!
b01100000 (
b00000110 )
b01111000 *
b00011110 +
1,
b01100000 /
b11000000 0
11
b00000110 4
b00000011 5
16
b01111000 9
b11110000 :
1;
b00011110 >
b00001111 ?
#14000000
0!
0,
01
06
0;
#15000000
1!
b11000000 (
b00000011 )
b11110000 *
b00001111 +
1,
b11000000 /
b10000000 0
11
b00000011 4
b00000001 5
16
b11110000 9
b11100001 :
1;
b00001111 >
b10000111 ?
#16000000
0!
0,
01
06
0;
#17000000
1!
b10000000 (
b00000001 )
b11100001 *
b10000111 +
1,
b10000000 /
b00000000 0
11
b00000001 4
b00000000 5
16
b11100001 9
b11000011 :
1;
b10000111 >
b11000011 ?
#18000000
0!
0,
01
06
0;
#19000000
1!
b00000000 (
b00000000 )
b11000011 *
b11000011 +
1,
b00000000 /
11
b00000000 4
16
b11000011 9
b10000111 :
1;
b11000011 >
b11100001 ?
#20000000
0!
0,
01
06
0;
#21000000
1!
b10000111 *
b11100001 +
1,
11
16
b10000111 9
b00001111 :
1;
b11100001 >
b11110000 ?
#22000000
0!
0,
01
06
0;
#23000000
1!
b00001111 *
b11110000 +
1,
11
16
b00001111 9
b00011110 :
1;
b11110000 >
b01111000 ?
#24000000
0!
0,
01
06
0;
#25000000
1!
b00011110 *
b01111000 +
1,
11
16
b00011110 9
b00111100 :
1;
b01111000 >
b00111100 ?
#26000000
0!
0,
01
06
0;
#27000000
1!
b00111100 *
b00111100 +
1,
11
16
b00111100 9
b01111000 :
1;
b00111100 >
b00011110 ?
#28000000
0!
0,
01
06
0;
#29000000
1!
b01111000 *
b00011110 +
1,
11
16
b01111000 9
b11110000 :
1;
b00011110 >
b00001111 ?
#30000000
0!
0,
01
06
0;
#31000000
1!
b11110000 *
b00001111 +
1,
11
16
b11110000 9
b11100001 :
1;
b00001111 >
b10000111 ?
#32000000
0!
0,
01
06
0;
#33000000
1!
b11100001 *
b10000111 +
1,
11
16
b11100001 9
b11000011 :
1;
b10000111 >
b11000011 ?
#34000000
0!
0,
01
06
0;
#35000000
1!
b11000011 *
b11000011 +
1,
11
16
b11000011 9
b10000111 :
1;
b11000011 >
b11100001 ?
#36000000
0!
0,
01
06
0;
#37000000
1!
b10000111 *
b11100001 +
1,
11
16
b10000111 9
b00001111 :
1;
b11100001 >
b11110000 ?
#38000000
0!
0,
01
06
0;
#39000000
1!
b00001111 *
b11110000 +
1,
11
16
b00001111 9
b00011110 :
1;
b11110000 >
b01111000 ?
#40000000
0!
0,
01
06
0;
#41000000
1!
b00011110 *
b01111000 +
1,
11
16
b00011110 9
b00111100 :
1;
b01111000 >
b00111100 ?
#42000000
0!
0,
01
06
0;
#43000000
1!
b00111100 *
b00111100 +
1,
11
16
b00111100 9
b01111000 :
1;
b00111100 >
b00011110 ?
#44000000
0!
0,
01
06
0;
#45000000
1!
b01111000 *
b00011110 +
1,
11
16
b01111000 9
b11110000 :
1;
b00011110 >
b00001111 ?
#46000000
0!
0,
01
06
0;
#47000000
1!
b11110000 *
b00001111 +
1,
11
16
b11110000 9
b11100001 :
1;
b00001111 >
b10000111 ?
#48000000
0!
0,
01
06
0;
#49000000
1!
b11100001 *
b10000111 +
1,
11
16
b11100001 9
b11000011 :
1;
b10000111 >
b11000011 ?
#50000000
0!
0,
01
06
0;
#51000000
1!
b11000011 *
b11000011 +
1,
11
16
b11000011 9
b10000111 :
1;
b11000011 >
b11100001 ?
#52000000
0!
0,
01
06
0;
#53000000
1!
b10000111 *
b11100001 +
1,
11
16
b10000111 9
b00001111 :
1;
b11100001 >
b11110000 ?
#54000000
0!
0,
01
06
0;
#55000000
1!
b00001111 *
b11110000 +
1,
11
16
b00001111 9
b00011110 :
1;
b11110000 >
b01111000 ?
#56000000
0!
0,
01
06
0;
#57000000
1!
b00011110 *
b01111000 +
1,
11
16
b00011110 9
b00111100 :
1;
b01111000 >
b00111100 ?
#58000000
0!
0,
01
06
0;
#59000000
1!
b00111100 *
b00111100 +
1,
11
16
b00111100 9
b01111000 :
1;
b00111100 >
b00011110 ?
#60000000
0!
0,
01
06
0;
#61000000
1!
b01111000 *
b00011110 +
1,
11
16
b01111000 9
b11110000 :
1;
b00011110 >
b00001111 ?
#62000000
0!
0,
01
06
0;
#63000000
1!
b11110000 *
b00001111 +
1,
11
16
b11110000 9
b11100001 :
1;
b00001111 >
b10000111 ?
#64000000
0!
0,
01
06
0;
#65000000
1!
b11100001 *
b10000111 +
1,
11
16
b11100001 9
b11000011 :
1;
b10000111 >
b11000011 ?
#66000000
0!
0,
01
06
0;
#67000000
1!
b11000011 *
b11000011 +
1,
11
16
b11000011 9
b10000111 :
1;
b11000011 >
b11100001 ?
#68000000
0!
0,
01
06
0;
#69000000
1!
b10000111 *
b11100001 +
1,
11
16
b10000111 9
b00001111 :
1;
b11100001 >
b11110000 ?
#70000000
0!
0,
01
06
0;
#71000000
1!
b00001111 *
b11110000 +
1,
11
16
b00001111 9
b00011110 :
1;
b11110000 >
b01111000 ?
#72000000
0!
0,
01
06
0;
#73000000
1!
b00011110 *
b01111000 +
1,
11
16
b00011110 9
b00111100 :
1;
b01111000 >
b00111100 ?
#74000000
0!
0,
01
06
0;
#75000000
1!
b00111100 *
b00111100 +
1,
11
16
b00111100 9
b01111000 :
1;
b00111100 >
b00011110 ?
#76000000
0!
0,
01
06
0;
#77000000
1!
b01111000 *
b00011110 +
1,
11
16
b01111000 9
b11110000 :
1;
b00011110 >
b00001111 ?
#78000000
0!
0,
01
06
0;
#79000000
1!
b11110000 *
b00001111 +
1,
11
16
b11110000 9
b11100001 :
1;
b00001111 >
b10000111 ?
